emoji_lexicon/__init__.py
emoji_lexicon/api.py
emoji_lexicon/build_data/__init__.py
emoji_lexicon/build_data/merge.py
emoji_lexicon/data/emoji.msgpack
emoji_lexicon/models/__init__.py
emoji_lexicon/models/catalog.py
emoji_lexicon/models/emoji.py
emoji_lexicon/unicode/__init__.py
emoji_lexicon/unicode/cldr_annotations_parser.py
emoji_lexicon/unicode/emoji_test_parser.py
emoji_lexicon/unicode/normalize.py
emoji_lexicon/unicode/types.py
emoji_lexicon-0.2.1.dist-info/METADATA
emoji_lexicon-0.2.1.dist-info/WHEEL
emoji_lexicon-0.2.1.dist-info/entry_points.txt
emoji_lexicon-0.2.1.dist-info/licenses/LICENSE
emoji_lexicon-0.2.1.dist-info/RECORD
