Metadata-Version: 2.4
Name: emoji-lexicon
Version: 0.2.1
Summary: A build-time generated emoji lexicon for Python
Project-URL: Homepage, https://github.com/kimikato/emoji-lexicon
Project-URL: Source, https://github.com/kimikato/emoji-lexicon
Project-URL: Issues, https://github.com/kimikato/emoji-lexicon/issues
Project-URL: Documentation, https://github.com/kimikato/emoji-lexicon/tree/main/docs
Author: Kiminori KATO
License: MIT License
License-File: LICENSE
Classifier: License :: OSI Approved :: MIT License
Classifier: Operating System :: OS Independent
Classifier: Programming Language :: Python
Classifier: Programming Language :: Python :: 3
Classifier: Programming Language :: Python :: 3.12
Requires-Python: >=3.12
Requires-Dist: msgpack>=1.0.7
Provides-Extra: dev
Requires-Dist: black; extra == 'dev'
Requires-Dist: build; extra == 'dev'
Requires-Dist: coverage; extra == 'dev'
Requires-Dist: flake8; extra == 'dev'
Requires-Dist: mypy>=1.9; extra == 'dev'
Requires-Dist: pytest>=8.0; extra == 'dev'
Requires-Dist: ruff>=0.4; extra == 'dev'
